mdpt/__init__.py
mdpt-0.1.dist-info/LICENSE
mdpt-0.1.dist-info/METADATA
mdpt-0.1.dist-info/WHEEL
mdpt-0.1.dist-info/top_level.txt
mdpt-0.1.dist-info/RECORD
