Metadata-Version: 2.1
Name: mdpt
Version: 0.1
Summary: protocol
Home-page: https://github.com/6d6b31/mdpt/
Author: 6d6b
Author-email: 6d6b31@gmail.com
License: UNKNOWN
Project-URL: Bug Tracker, https://github.com/6d6b31/mdpt/issues
Platform: UNKNOWN
Classifier: Programming Language :: Python :: 3
Classifier: License :: OSI Approved :: MIT License
Classifier: Operating System :: OS Independent
Requires-Python: >=3.6
